text_selection/__init__.py
text_selection/cover_applied.py
text_selection/cover_export.py
text_selection/cover_methods.py
text_selection/greedy_kld_applied.py
text_selection/greedy_kld_export.py
text_selection/greedy_kld_methods.py
text_selection/metrics_applied.py
text_selection/metrics_export.py
text_selection/metrics_methods.py
text_selection/random_applied.py
text_selection/random_export.py
text_selection/random_method.py
text_selection/selection.py
text_selection/utils.py
text_selection/common/__init__.py
text_selection/common/durations_iterator.py
text_selection/common/filter_durations.py
text_selection/common/helper.py
text_selection/common/mapping_iterator.py
text_selection/common/ngram_extractor.py
text_selection/common/ngram_extractor2.py
text_selection/greedy/__init__.py
text_selection/greedy/greedy_N_epoch_iterator.py
text_selection/greedy/greedy_N_iterator.py
text_selection/greedy/greedy_applied.py
text_selection/greedy/greedy_epoch_iterator.py
text_selection/greedy/greedy_export.py
text_selection/greedy/greedy_iterator.py
text_selection/greedy/greedy_methods.py
text_selection/greedy/main.py
text_selection/greedy/optimized_greedy_N_iterator.py
text_selection/greedy/optimized_greedy_iterator.py
text_selection/kld/__init__.py
text_selection/kld/custom_kld_iterator.py
text_selection/kld/kld_iterator.py
text_selection/kld/main.py
text_selection/kld/optimized_kld_iterator.py
text_selection/random/__init__.py
text_selection/random/main.py
text_selection/random/random_iterator.py
text_selection_cli/__init__.py
text_selection_cli/argparse_helper.py
text_selection_cli/cli.py
text_selection_cli/datasets.py
text_selection_cli/default_args.py
text_selection_cli/export.py
text_selection_cli/filtering.py
text_selection_cli/globals.py
text_selection_cli/io_handling.py
text_selection_cli/logging_configuration.py
text_selection_cli/n_grams.py
text_selection_cli/selection.py
text_selection_cli/sorting.py
text_selection_cli/statistics.py
text_selection_cli/subset.py
text_selection-0.0.3.dist-info/LICENSE
text_selection-0.0.3.dist-info/METADATA
text_selection-0.0.3.dist-info/WHEEL
text_selection-0.0.3.dist-info/entry_points.txt
text_selection-0.0.3.dist-info/top_level.txt
text_selection-0.0.3.dist-info/RECORD
