Metadata-Version: 2.1
Name: text-selection
Version: 0.0.3
Summary: Command-line interface (CLI) to select lines of a text file.
Author-email: Stefan Taubert <pypi@stefantaubert.com>
Maintainer-email: Stefan Taubert <pypi@stefantaubert.com>
License: MIT
Project-URL: Homepage, https://github.com/stefantaubert/text-selection
Project-URL: Issues, https://github.com/stefantaubert/text-selection/issues
Keywords: Text-to-speech,Speech synthesis,Corpus,Utils,Language,Linguistics
Classifier: Development Status :: 2 - Pre-Alpha
Classifier: Operating System :: OS Independent
Classifier: Operating System :: MacOS
Classifier: Operating System :: POSIX
Classifier: Operating System :: POSIX :: BSD
Classifier: Operating System :: POSIX :: Linux
Classifier: Operating System :: Unix
Classifier: Operating System :: Microsoft :: Windows
Classifier: Programming Language :: Python
Classifier: Programming Language :: Python :: 3
Classifier: Programming Language :: Python :: 3.8
Classifier: Programming Language :: Python :: 3.9
Classifier: Programming Language :: Python :: 3.10
Classifier: Programming Language :: Python :: 3.11
Classifier: License :: OSI Approved :: MIT License
Requires-Python: <4,>=3.8
License-File: LICENSE
Requires-Dist: tqdm
Requires-Dist: numpy
Requires-Dist: scipy
Requires-Dist: pandas
Requires-Dist: ordered-set (>=4.1.0)
